archipelago/__init__.py
archipelago/analysis.py
archipelago/io.py
archipelago/place.py
archipelago/pnr_.py
archipelago/pnr_graph.py
archipelago/power.py
archipelago/retime.py
archipelago/route.py
archipelago/sta.py
archipelago/sta_delays.json
archipelago/util.py
archipelago/virtualize.py
archipelago-0.0.10.data/data/sta_delays/sta_delays.json
archipelago-0.0.10.dist-info/METADATA
archipelago-0.0.10.dist-info/WHEEL
archipelago-0.0.10.dist-info/top_level.txt
archipelago-0.0.10.dist-info/RECORD
